pyvista_view/__init__.py
pyvista_view/__main__.py
pyvista_view/py.typed
pyvista_view-0.0.1.dist-info/LICENSE
pyvista_view-0.0.1.dist-info/METADATA
pyvista_view-0.0.1.dist-info/WHEEL
pyvista_view-0.0.1.dist-info/top_level.txt
pyvista_view-0.0.1.dist-info/RECORD
