Metadata-Version: 2.1
Name: pyvista-view
Version: 0.0.1
Summary: A pythonic interface to the Qt Graphics View Framework using qtpy
Author-email: Adam Hendry <adam.grant.hendry@gmail.com>
License: MIT
Classifier: License :: OSI Approved :: Apache Software License
Classifier: Operating System :: Microsoft :: Windows :: Windows 10
Classifier: Operating System :: MacOS :: MacOS X
Classifier: Operating System :: POSIX :: Linux
Classifier: Programming Language :: Python :: 3.9
Classifier: Programming Language :: Python :: 3.10
Classifier: Programming Language :: Python :: 3.11
Classifier: Programming Language :: Python :: 3.12
Requires-Python: <3.13,>=3.9
License-File: LICENSE
Requires-Dist: qtpy>=2.4.2
Provides-Extra: dev
Requires-Dist: pyvista-view[docs,format,github,license,test]; extra == "dev"
Provides-Extra: docs
Requires-Dist: appdirs>=1.4.4; extra == "docs"
Requires-Dist: Jinja2<3.1,>=3.0; extra == "docs"
Requires-Dist: numpydoc>=1.4.0; extra == "docs"
Requires-Dist: seedir>=0.3.0; extra == "docs"
Requires-Dist: sphinx<8.2.0; extra == "docs"
Requires-Dist: sphinx-book-theme>=0.3.3; extra == "docs"
Requires-Dist: sphinxcontrib-email>=0.3.5; extra == "docs"
Requires-Dist: sphinxcontrib-napoleon>=0.7; extra == "docs"
Requires-Dist: tomli>=2.0.1; extra == "docs"
Provides-Extra: format
Requires-Dist: pre-commit>=2.18.1; extra == "format"
Requires-Dist: mypy>=0.991; extra == "format"
Requires-Dist: mypy-extensions>=0.4.3; extra == "format"
Requires-Dist: tqdm-stubs>=0.2.0; extra == "format"
Requires-Dist: types-beautifulsoup4>=4.11.6.1; extra == "format"
Requires-Dist: types-setuptools>=57.4.17; extra == "format"
Requires-Dist: typing-extensions>=4.2.0; extra == "format"
Provides-Extra: github
Requires-Dist: pytest-github-actions-annotate-failures>=0.2.0; extra == "github"
Provides-Extra: license
Requires-Dist: licensecheck>=2023.3; extra == "license"
Provides-Extra: test
Requires-Dist: coverage[toml]>=6.4; extra == "test"
Requires-Dist: hypothesis>=6.46.2; extra == "test"
Requires-Dist: pytest>=7.1.2; extra == "test"
Requires-Dist: pytest-cov>=3.0.0; extra == "test"
Requires-Dist: pytest-doctestplus>=0.12.0; extra == "test"
Requires-Dist: pytest-env>=0.6.2; extra == "test"
Requires-Dist: pytest-memprof>=0.2.0; extra == "test"
Requires-Dist: pytest-mock>=3.7.0; extra == "test"
Requires-Dist: pytest-qt>=4.4.0; extra == "test"
Requires-Dist: pytest-randomly>=3.11.0; extra == "test"
Requires-Dist: pytest-xdist>=2.5.0; extra == "test"
